CL_Auto_Library/CL_Auto_Keywords.py
CL_Auto_Library/__init__.py
CL_Auto_Library-1.1.5.3.dist-info/LICENSE.txt
CL_Auto_Library-1.1.5.3.dist-info/METADATA
CL_Auto_Library-1.1.5.3.dist-info/WHEEL
CL_Auto_Library-1.1.5.3.dist-info/top_level.txt
CL_Auto_Library-1.1.5.3.dist-info/RECORD
